reppy/__init__.py
reppy/cache.py
reppy/exceptions.py
reppy/parser.py
reppy2-0.3.6.dist-info/LICENSE
reppy2-0.3.6.dist-info/METADATA
reppy2-0.3.6.dist-info/WHEEL
reppy2-0.3.6.dist-info/top_level.txt
reppy2-0.3.6.dist-info/RECORD
